{"type":"Metric","data":{"name":"vus","type":"gauge","contains":"default","thresholds":[],"submetrics":null},"metric":"vus"}
{"metric":"vus","type":"Point","data":{"time":"2023-06-14T17:45:54.54722+07:00","value":1,"tags":{}}}
{"type":"Metric","data":{"name":"vus_max","type":"gauge","contains":"default","thresholds":[],"submetrics":null},"metric":"vus_max"}
{"metric":"vus_max","type":"Point","data":{"time":"2023-06-14T17:45:54.54722+07:00","value":1,"tags":{}}}
{"type":"Metric","data":{"name":"http_reqs","type":"counter","contains":"default","thresholds":[],"submetrics":null},"metric":"http_reqs"}
{"metric":"http_reqs","type":"Point","data":{"time":"2023-06-14T17:45:54.664743+07:00","value":1,"tags":{"expected_response":"true","group":"","method":"POST","name":"https://api-staging.jurnal.id/pim/warehouses","proto":"HTTP/2.0","scenario":"default","status":"200","tls_version":"tls1.2","url":"https://api-staging.jurnal.id/pim/warehouses"}}}
{"type":"Metric","data":{"name":"http_req_duration","type":"trend","contains":"time","thresholds":[],"submetrics":[{"name":"http_req_duration{expected_response:true}","suffix":"expected_response:true","tags":{"expected_response":"true"}}]},"metric":"http_req_duration"}
{"metric":"http_req_duration","type":"Point","data":{"time":"2023-06-14T17:45:54.664743+07:00","value":614.876,"tags":{"expected_response":"true","group":"","method":"POST","name":"https://api-staging.jurnal.id/pim/warehouses","proto":"HTTP/2.0","scenario":"default","status":"200","tls_version":"tls1.2","url":"https://api-staging.jurnal.id/pim/warehouses"}}}
{"type":"Metric","data":{"name":"http_req_blocked","type":"trend","contains":"time","thresholds":[],"submetrics":null},"metric":"http_req_blocked"}
{"metric":"http_req_blocked","type":"Point","data":{"time":"2023-06-14T17:45:54.664743+07:00","value":504.66,"tags":{"expected_response":"true","group":"","method":"POST","name":"https://api-staging.jurnal.id/pim/warehouses","proto":"HTTP/2.0","scenario":"default","status":"200","tls_version":"tls1.2","url":"https://api-staging.jurnal.id/pim/warehouses"}}}
{"type":"Metric","data":{"name":"http_req_connecting","type":"trend","contains":"time","thresholds":[],"submetrics":null},"metric":"http_req_connecting"}
{"metric":"http_req_connecting","type":"Point","data":{"time":"2023-06-14T17:45:54.664743+07:00","value":119.993,"tags":{"expected_response":"true","group":"","method":"POST","name":"https://api-staging.jurnal.id/pim/warehouses","proto":"HTTP/2.0","scenario":"default","status":"200","tls_version":"tls1.2","url":"https://api-staging.jurnal.id/pim/warehouses"}}}
{"type":"Metric","data":{"name":"http_req_tls_handshaking","type":"trend","contains":"time","thresholds":[],"submetrics":null},"metric":"http_req_tls_handshaking"}
{"metric":"http_req_tls_handshaking","type":"Point","data":{"time":"2023-06-14T17:45:54.664743+07:00","value":268.4,"tags":{"expected_response":"true","group":"","method":"POST","name":"https://api-staging.jurnal.id/pim/warehouses","proto":"HTTP/2.0","scenario":"default","status":"200","tls_version":"tls1.2","url":"https://api-staging.jurnal.id/pim/warehouses"}}}
{"type":"Metric","data":{"name":"http_req_sending","type":"trend","contains":"time","thresholds":[],"submetrics":null},"metric":"http_req_sending"}
{"metric":"http_req_sending","type":"Point","data":{"time":"2023-06-14T17:45:54.664743+07:00","value":0.998,"tags":{"expected_response":"true","group":"","method":"POST","name":"https://api-staging.jurnal.id/pim/warehouses","proto":"HTTP/2.0","scenario":"default","status":"200","tls_version":"tls1.2","url":"https://api-staging.jurnal.id/pim/warehouses"}}}
{"type":"Metric","data":{"name":"http_req_waiting","type":"trend","contains":"time","thresholds":[],"submetrics":null},"metric":"http_req_waiting"}
{"metric":"http_req_waiting","type":"Point","data":{"time":"2023-06-14T17:45:54.664743+07:00","value":613.693,"tags":{"expected_response":"true","group":"","method":"POST","name":"https://api-staging.jurnal.id/pim/warehouses","proto":"HTTP/2.0","scenario":"default","status":"200","tls_version":"tls1.2","url":"https://api-staging.jurnal.id/pim/warehouses"}}}
{"type":"Metric","data":{"name":"http_req_receiving","type":"trend","contains":"time","thresholds":[],"submetrics":null},"metric":"http_req_receiving"}
{"metric":"http_req_receiving","type":"Point","data":{"time":"2023-06-14T17:45:54.664743+07:00","value":0.185,"tags":{"expected_response":"true","group":"","method":"POST","name":"https://api-staging.jurnal.id/pim/warehouses","proto":"HTTP/2.0","scenario":"default","status":"200","tls_version":"tls1.2","url":"https://api-staging.jurnal.id/pim/warehouses"}}}
{"type":"Metric","data":{"name":"http_req_failed","type":"rate","contains":"default","thresholds":[],"submetrics":null},"metric":"http_req_failed"}
{"metric":"http_req_failed","type":"Point","data":{"time":"2023-06-14T17:45:54.664743+07:00","value":0,"tags":{"expected_response":"true","group":"","method":"POST","name":"https://api-staging.jurnal.id/pim/warehouses","proto":"HTTP/2.0","scenario":"default","status":"200","tls_version":"tls1.2","url":"https://api-staging.jurnal.id/pim/warehouses"}}}
{"type":"Metric","data":{"name":"data_sent","type":"counter","contains":"data","thresholds":[],"submetrics":null},"metric":"data_sent"}
{"metric":"data_sent","type":"Point","data":{"time":"2023-06-14T17:45:55.166227+07:00","value":986,"tags":{"group":"","scenario":"default"}}}
{"type":"Metric","data":{"name":"data_received","type":"counter","contains":"data","thresholds":[],"submetrics":null},"metric":"data_received"}
{"metric":"data_received","type":"Point","data":{"time":"2023-06-14T17:45:55.166227+07:00","value":7046,"tags":{"group":"","scenario":"default"}}}
{"type":"Metric","data":{"name":"iteration_duration","type":"trend","contains":"time","thresholds":[],"submetrics":null},"metric":"iteration_duration"}
{"metric":"iteration_duration","type":"Point","data":{"time":"2023-06-14T17:45:55.166227+07:00","value":1620.852037,"tags":{"group":"","scenario":"default"}}}
{"type":"Metric","data":{"name":"iterations","type":"counter","contains":"default","thresholds":[],"submetrics":null},"metric":"iterations"}
{"metric":"iterations","type":"Point","data":{"time":"2023-06-14T17:45:55.166227+07:00","value":1,"tags":{"group":"","scenario":"default"}}}
{"metric":"vus","type":"Point","data":{"time":"2023-06-14T17:45:55.546698+07:00","value":1,"tags":{}}}
{"metric":"vus_max","type":"Point","data":{"time":"2023-06-14T17:45:55.546698+07:00","value":1,"tags":{}}}
{"metric":"http_reqs","type":"Point","data":{"time":"2023-06-14T17:45:55.894333+07:00","value":1,"tags":{"expected_response":"true","group":"","method":"POST","name":"https://api-staging.jurnal.id/pim/warehouses","proto":"HTTP/2.0","scenario":"default","status":"200","tls_version":"tls1.2","url":"https://api-staging.jurnal.id/pim/warehouses"}}}
{"metric":"http_req_duration","type":"Point","data":{"time":"2023-06-14T17:45:55.894333+07:00","value":727.55,"tags":{"expected_response":"true","group":"","method":"POST","name":"https://api-staging.jurnal.id/pim/warehouses","proto":"HTTP/2.0","scenario":"default","status":"200","tls_version":"tls1.2","url":"https://api-staging.jurnal.id/pim/warehouses"}}}
{"metric":"http_req_blocked","type":"Point","data":{"time":"2023-06-14T17:45:55.894333+07:00","value":0.002,"tags":{"expected_response":"true","group":"","method":"POST","name":"https://api-staging.jurnal.id/pim/warehouses","proto":"HTTP/2.0","scenario":"default","status":"200","tls_version":"tls1.2","url":"https://api-staging.jurnal.id/pim/warehouses"}}}
{"metric":"http_req_connecting","type":"Point","data":{"time":"2023-06-14T17:45:55.894333+07:00","value":0,"tags":{"expected_response":"true","group":"","method":"POST","name":"https://api-staging.jurnal.id/pim/warehouses","proto":"HTTP/2.0","scenario":"default","status":"200","tls_version":"tls1.2","url":"https://api-staging.jurnal.id/pim/warehouses"}}}
{"metric":"http_req_tls_handshaking","type":"Point","data":{"time":"2023-06-14T17:45:55.894333+07:00","value":0,"tags":{"expected_response":"true","group":"","method":"POST","name":"https://api-staging.jurnal.id/pim/warehouses","proto":"HTTP/2.0","scenario":"default","status":"200","tls_version":"tls1.2","url":"https://api-staging.jurnal.id/pim/warehouses"}}}
{"metric":"http_req_sending","type":"Point","data":{"time":"2023-06-14T17:45:55.894333+07:00","value":0.209,"tags":{"expected_response":"true","group":"","method":"POST","name":"https://api-staging.jurnal.id/pim/warehouses","proto":"HTTP/2.0","scenario":"default","status":"200","tls_version":"tls1.2","url":"https://api-staging.jurnal.id/pim/warehouses"}}}
{"metric":"http_req_waiting","type":"Point","data":{"time":"2023-06-14T17:45:55.894333+07:00","value":727.127,"tags":{"expected_response":"true","group":"","method":"POST","name":"https://api-staging.jurnal.id/pim/warehouses","proto":"HTTP/2.0","scenario":"default","status":"200","tls_version":"tls1.2","url":"https://api-staging.jurnal.id/pim/warehouses"}}}
{"metric":"http_req_receiving","type":"Point","data":{"time":"2023-06-14T17:45:55.894333+07:00","value":0.214,"tags":{"expected_response":"true","group":"","method":"POST","name":"https://api-staging.jurnal.id/pim/warehouses","proto":"HTTP/2.0","scenario":"default","status":"200","tls_version":"tls1.2","url":"https://api-staging.jurnal.id/pim/warehouses"}}}
{"metric":"http_req_failed","type":"Point","data":{"time":"2023-06-14T17:45:55.894333+07:00","value":0,"tags":{"expected_response":"true","group":"","method":"POST","name":"https://api-staging.jurnal.id/pim/warehouses","proto":"HTTP/2.0","scenario":"default","status":"200","tls_version":"tls1.2","url":"https://api-staging.jurnal.id/pim/warehouses"}}}
{"metric":"data_sent","type":"Point","data":{"time":"2023-06-14T17:45:56.398289+07:00","value":225,"tags":{"group":"","scenario":"default"}}}
{"metric":"data_received","type":"Point","data":{"time":"2023-06-14T17:45:56.398289+07:00","value":816,"tags":{"group":"","scenario":"default"}}}
{"metric":"iteration_duration","type":"Point","data":{"time":"2023-06-14T17:45:56.398289+07:00","value":1231.985483,"tags":{"group":"","scenario":"default"}}}
{"metric":"iterations","type":"Point","data":{"time":"2023-06-14T17:45:56.398289+07:00","value":1,"tags":{"group":"","scenario":"default"}}}
{"metric":"vus","type":"Point","data":{"time":"2023-06-14T17:45:56.547537+07:00","value":1,"tags":{}}}
{"metric":"vus_max","type":"Point","data":{"time":"2023-06-14T17:45:56.547537+07:00","value":1,"tags":{}}}
{"metric":"http_reqs","type":"Point","data":{"time":"2023-06-14T17:45:56.927539+07:00","value":1,"tags":{"expected_response":"true","group":"","method":"POST","name":"https://api-staging.jurnal.id/pim/warehouses","proto":"HTTP/2.0","scenario":"default","status":"200","tls_version":"tls1.2","url":"https://api-staging.jurnal.id/pim/warehouses"}}}
{"metric":"http_req_duration","type":"Point","data":{"time":"2023-06-14T17:45:56.927539+07:00","value":528.819,"tags":{"expected_response":"true","group":"","method":"POST","name":"https://api-staging.jurnal.id/pim/warehouses","proto":"HTTP/2.0","scenario":"default","status":"200","tls_version":"tls1.2","url":"https://api-staging.jurnal.id/pim/warehouses"}}}
{"metric":"http_req_blocked","type":"Point","data":{"time":"2023-06-14T17:45:56.927539+07:00","value":0.001,"tags":{"expected_response":"true","group":"","method":"POST","name":"https://api-staging.jurnal.id/pim/warehouses","proto":"HTTP/2.0","scenario":"default","status":"200","tls_version":"tls1.2","url":"https://api-staging.jurnal.id/pim/warehouses"}}}
{"metric":"http_req_connecting","type":"Point","data":{"time":"2023-06-14T17:45:56.927539+07:00","value":0,"tags":{"expected_response":"true","group":"","method":"POST","name":"https://api-staging.jurnal.id/pim/warehouses","proto":"HTTP/2.0","scenario":"default","status":"200","tls_version":"tls1.2","url":"https://api-staging.jurnal.id/pim/warehouses"}}}
{"metric":"http_req_tls_handshaking","type":"Point","data":{"time":"2023-06-14T17:45:56.927539+07:00","value":0,"tags":{"expected_response":"true","group":"","method":"POST","name":"https://api-staging.jurnal.id/pim/warehouses","proto":"HTTP/2.0","scenario":"default","status":"200","tls_version":"tls1.2","url":"https://api-staging.jurnal.id/pim/warehouses"}}}
{"metric":"http_req_sending","type":"Point","data":{"time":"2023-06-14T17:45:56.927539+07:00","value":0.345,"tags":{"expected_response":"true","group":"","method":"POST","name":"https://api-staging.jurnal.id/pim/warehouses","proto":"HTTP/2.0","scenario":"default","status":"200","tls_version":"tls1.2","url":"https://api-staging.jurnal.id/pim/warehouses"}}}
{"metric":"http_req_waiting","type":"Point","data":{"time":"2023-06-14T17:45:56.927539+07:00","value":528.233,"tags":{"expected_response":"true","group":"","method":"POST","name":"https://api-staging.jurnal.id/pim/warehouses","proto":"HTTP/2.0","scenario":"default","status":"200","tls_version":"tls1.2","url":"https://api-staging.jurnal.id/pim/warehouses"}}}
{"metric":"http_req_receiving","type":"Point","data":{"time":"2023-06-14T17:45:56.927539+07:00","value":0.241,"tags":{"expected_response":"true","group":"","method":"POST","name":"https://api-staging.jurnal.id/pim/warehouses","proto":"HTTP/2.0","scenario":"default","status":"200","tls_version":"tls1.2","url":"https://api-staging.jurnal.id/pim/warehouses"}}}
{"metric":"http_req_failed","type":"Point","data":{"time":"2023-06-14T17:45:56.927539+07:00","value":0,"tags":{"expected_response":"true","group":"","method":"POST","name":"https://api-staging.jurnal.id/pim/warehouses","proto":"HTTP/2.0","scenario":"default","status":"200","tls_version":"tls1.2","url":"https://api-staging.jurnal.id/pim/warehouses"}}}
{"metric":"data_sent","type":"Point","data":{"time":"2023-06-14T17:45:57.430076+07:00","value":220,"tags":{"group":"","scenario":"default"}}}
{"metric":"data_received","type":"Point","data":{"time":"2023-06-14T17:45:57.430076+07:00","value":815,"tags":{"group":"","scenario":"default"}}}
{"metric":"iteration_duration","type":"Point","data":{"time":"2023-06-14T17:45:57.430076+07:00","value":1031.687369,"tags":{"group":"","scenario":"default"}}}
{"metric":"iterations","type":"Point","data":{"time":"2023-06-14T17:45:57.430076+07:00","value":1,"tags":{"group":"","scenario":"default"}}}
{"metric":"vus","type":"Point","data":{"time":"2023-06-14T17:45:57.544141+07:00","value":1,"tags":{}}}
{"metric":"vus_max","type":"Point","data":{"time":"2023-06-14T17:45:57.544141+07:00","value":1,"tags":{}}}
{"metric":"http_reqs","type":"Point","data":{"time":"2023-06-14T17:45:57.849006+07:00","value":1,"tags":{"expected_response":"true","group":"","method":"POST","name":"https://api-staging.jurnal.id/pim/warehouses","proto":"HTTP/2.0","scenario":"default","status":"200","tls_version":"tls1.2","url":"https://api-staging.jurnal.id/pim/warehouses"}}}
{"metric":"http_req_duration","type":"Point","data":{"time":"2023-06-14T17:45:57.849006+07:00","value":418.512,"tags":{"expected_response":"true","group":"","method":"POST","name":"https://api-staging.jurnal.id/pim/warehouses","proto":"HTTP/2.0","scenario":"default","status":"200","tls_version":"tls1.2","url":"https://api-staging.jurnal.id/pim/warehouses"}}}
{"metric":"http_req_blocked","type":"Point","data":{"time":"2023-06-14T17:45:57.849006+07:00","value":0.002,"tags":{"expected_response":"true","group":"","method":"POST","name":"https://api-staging.jurnal.id/pim/warehouses","proto":"HTTP/2.0","scenario":"default","status":"200","tls_version":"tls1.2","url":"https://api-staging.jurnal.id/pim/warehouses"}}}
{"metric":"http_req_connecting","type":"Point","data":{"time":"2023-06-14T17:45:57.849006+07:00","value":0,"tags":{"expected_response":"true","group":"","method":"POST","name":"https://api-staging.jurnal.id/pim/warehouses","proto":"HTTP/2.0","scenario":"default","status":"200","tls_version":"tls1.2","url":"https://api-staging.jurnal.id/pim/warehouses"}}}
{"metric":"http_req_tls_handshaking","type":"Point","data":{"time":"2023-06-14T17:45:57.849006+07:00","value":0,"tags":{"expected_response":"true","group":"","method":"POST","name":"https://api-staging.jurnal.id/pim/warehouses","proto":"HTTP/2.0","scenario":"default","status":"200","tls_version":"tls1.2","url":"https://api-staging.jurnal.id/pim/warehouses"}}}
{"metric":"http_req_sending","type":"Point","data":{"time":"2023-06-14T17:45:57.849006+07:00","value":0.292,"tags":{"expected_response":"true","group":"","method":"POST","name":"https://api-staging.jurnal.id/pim/warehouses","proto":"HTTP/2.0","scenario":"default","status":"200","tls_version":"tls1.2","url":"https://api-staging.jurnal.id/pim/warehouses"}}}
{"metric":"http_req_waiting","type":"Point","data":{"time":"2023-06-14T17:45:57.849006+07:00","value":416.138,"tags":{"expected_response":"true","group":"","method":"POST","name":"https://api-staging.jurnal.id/pim/warehouses","proto":"HTTP/2.0","scenario":"default","status":"200","tls_version":"tls1.2","url":"https://api-staging.jurnal.id/pim/warehouses"}}}
{"metric":"http_req_receiving","type":"Point","data":{"time":"2023-06-14T17:45:57.849006+07:00","value":2.082,"tags":{"expected_response":"true","group":"","method":"POST","name":"https://api-staging.jurnal.id/pim/warehouses","proto":"HTTP/2.0","scenario":"default","status":"200","tls_version":"tls1.2","url":"https://api-staging.jurnal.id/pim/warehouses"}}}
{"metric":"http_req_failed","type":"Point","data":{"time":"2023-06-14T17:45:57.849006+07:00","value":0,"tags":{"expected_response":"true","group":"","method":"POST","name":"https://api-staging.jurnal.id/pim/warehouses","proto":"HTTP/2.0","scenario":"default","status":"200","tls_version":"tls1.2","url":"https://api-staging.jurnal.id/pim/warehouses"}}}
{"metric":"data_sent","type":"Point","data":{"time":"2023-06-14T17:45:58.349847+07:00","value":226,"tags":{"group":"","scenario":"default"}}}
{"metric":"data_received","type":"Point","data":{"time":"2023-06-14T17:45:58.349847+07:00","value":816,"tags":{"group":"","scenario":"default"}}}
{"metric":"iteration_duration","type":"Point","data":{"time":"2023-06-14T17:45:58.349847+07:00","value":919.710933,"tags":{"group":"","scenario":"default"}}}
{"metric":"iterations","type":"Point","data":{"time":"2023-06-14T17:45:58.349847+07:00","value":1,"tags":{"group":"","scenario":"default"}}}
{"metric":"vus","type":"Point","data":{"time":"2023-06-14T17:45:58.546557+07:00","value":1,"tags":{}}}
{"metric":"vus_max","type":"Point","data":{"time":"2023-06-14T17:45:58.546557+07:00","value":1,"tags":{}}}
{"metric":"http_reqs","type":"Point","data":{"time":"2023-06-14T17:45:59.486067+07:00","value":1,"tags":{"expected_response":"true","group":"","method":"POST","name":"https://api-staging.jurnal.id/pim/warehouses","proto":"HTTP/2.0","scenario":"default","status":"200","tls_version":"tls1.2","url":"https://api-staging.jurnal.id/pim/warehouses"}}}
{"metric":"http_req_duration","type":"Point","data":{"time":"2023-06-14T17:45:59.486067+07:00","value":1135.883,"tags":{"expected_response":"true","group":"","method":"POST","name":"https://api-staging.jurnal.id/pim/warehouses","proto":"HTTP/2.0","scenario":"default","status":"200","tls_version":"tls1.2","url":"https://api-staging.jurnal.id/pim/warehouses"}}}
{"metric":"http_req_blocked","type":"Point","data":{"time":"2023-06-14T17:45:59.486067+07:00","value":0.001,"tags":{"expected_response":"true","group":"","method":"POST","name":"https://api-staging.jurnal.id/pim/warehouses","proto":"HTTP/2.0","scenario":"default","status":"200","tls_version":"tls1.2","url":"https://api-staging.jurnal.id/pim/warehouses"}}}
{"metric":"http_req_connecting","type":"Point","data":{"time":"2023-06-14T17:45:59.486067+07:00","value":0,"tags":{"expected_response":"true","group":"","method":"POST","name":"https://api-staging.jurnal.id/pim/warehouses","proto":"HTTP/2.0","scenario":"default","status":"200","tls_version":"tls1.2","url":"https://api-staging.jurnal.id/pim/warehouses"}}}
{"metric":"http_req_tls_handshaking","type":"Point","data":{"time":"2023-06-14T17:45:59.486067+07:00","value":0,"tags":{"expected_response":"true","group":"","method":"POST","name":"https://api-staging.jurnal.id/pim/warehouses","proto":"HTTP/2.0","scenario":"default","status":"200","tls_version":"tls1.2","url":"https://api-staging.jurnal.id/pim/warehouses"}}}
{"metric":"http_req_sending","type":"Point","data":{"time":"2023-06-14T17:45:59.486067+07:00","value":0.216,"tags":{"expected_response":"true","group":"","method":"POST","name":"https://api-staging.jurnal.id/pim/warehouses","proto":"HTTP/2.0","scenario":"default","status":"200","tls_version":"tls1.2","url":"https://api-staging.jurnal.id/pim/warehouses"}}}
{"metric":"http_req_waiting","type":"Point","data":{"time":"2023-06-14T17:45:59.486067+07:00","value":1135.398,"tags":{"expected_response":"true","group":"","method":"POST","name":"https://api-staging.jurnal.id/pim/warehouses","proto":"HTTP/2.0","scenario":"default","status":"200","tls_version":"tls1.2","url":"https://api-staging.jurnal.id/pim/warehouses"}}}
{"metric":"http_req_receiving","type":"Point","data":{"time":"2023-06-14T17:45:59.486067+07:00","value":0.269,"tags":{"expected_response":"true","group":"","method":"POST","name":"https://api-staging.jurnal.id/pim/warehouses","proto":"HTTP/2.0","scenario":"default","status":"200","tls_version":"tls1.2","url":"https://api-staging.jurnal.id/pim/warehouses"}}}
{"metric":"http_req_failed","type":"Point","data":{"time":"2023-06-14T17:45:59.486067+07:00","value":0,"tags":{"expected_response":"true","group":"","method":"POST","name":"https://api-staging.jurnal.id/pim/warehouses","proto":"HTTP/2.0","scenario":"default","status":"200","tls_version":"tls1.2","url":"https://api-staging.jurnal.id/pim/warehouses"}}}
{"metric":"vus","type":"Point","data":{"time":"2023-06-14T17:45:59.54332+07:00","value":1,"tags":{}}}
{"metric":"vus_max","type":"Point","data":{"time":"2023-06-14T17:45:59.54332+07:00","value":1,"tags":{}}}
{"metric":"data_sent","type":"Point","data":{"time":"2023-06-14T17:45:59.988626+07:00","value":220,"tags":{"group":"","scenario":"default"}}}
{"metric":"data_received","type":"Point","data":{"time":"2023-06-14T17:45:59.988626+07:00","value":815,"tags":{"group":"","scenario":"default"}}}
{"metric":"iteration_duration","type":"Point","data":{"time":"2023-06-14T17:45:59.988626+07:00","value":1638.707634,"tags":{"group":"","scenario":"default"}}}
{"metric":"iterations","type":"Point","data":{"time":"2023-06-14T17:45:59.988626+07:00","value":1,"tags":{"group":"","scenario":"default"}}}
